__init__.py
fastinject/__init__.py
fastinject/decorators.py
fastinject/loggers.py
fastinject/registry.py
fastinject/service_config.py
fastinject/type_helpers.py
fastinject-0.0.4.dist-info/METADATA
fastinject-0.0.4.dist-info/WHEEL
fastinject-0.0.4.dist-info/top_level.txt
fastinject-0.0.4.dist-info/RECORD
