Metadata-Version: 2.1
Name: fastinject
Version: 0.0.4
Summary: Easy dependency injection in Python.
Author-email: Mike Huls <mikehuls42@gmail.com>
Project-URL: Homepage, https://github.com/mike-huls/fastinject
Project-URL: Bug Tracker, https://github.com/mike-huls/fastinject/issues
Project-URL: Documentation, https://github.com/mike-huls/fastinject/blob/master/README.md/
Project-URL: Changelog, https://github.com/mike-huls/fastinject/blob/master/CHANGELOG.md/
Project-URL: Source, https://github.com/mike-huls/fastinject/
Project-URL: Say Thanks!, https://www.buymeacoffee.com/mikehuls
Keywords: dependency injection,injection,decouple,decoupled,inversion
Classifier: Development Status :: 2 - Pre-Alpha
Classifier: Intended Audience :: Developers
Classifier: Intended Audience :: Information Technology
Classifier: Intended Audience :: System Administrators
Classifier: Operating System :: OS Independent
Classifier: License :: OSI Approved :: MIT License
Classifier: Topic :: Software Development :: Libraries :: Python Modules
Classifier: Topic :: Software Development :: Libraries
Classifier: Topic :: Software Development
Classifier: Programming Language :: Python
Classifier: Programming Language :: Python :: 3
Classifier: Programming Language :: Python :: 3 :: Only
Classifier: Programming Language :: Python :: 3.9
Classifier: Programming Language :: Python :: 3.10
Classifier: Programming Language :: Python :: 3.11
Classifier: Programming Language :: Python :: 3.12
Classifier: Programming Language :: Python :: 3.13
Classifier: Programming Language :: Python :: Implementation :: CPython
Classifier: License :: OSI Approved :: MIT License
Requires-Python: >=3.9
Requires-Dist: injector >=0.22.0
